junto_utils/__init__.py
junto_utils/numbers.py
junto_utils/tests.py
junto_utils/restframework/__init__.py
junto_utils/restframework/authentication.py
junto_utils/restframework/exceptions.py
junto_utils/restframework/fields.py
junto_utils/restframework/pagination.py
junto_utils/restframework/permissions.py
junto_utils/restframework/serializers.py
junto_utils-0.0.7.dist-info/DESCRIPTION.rst
junto_utils-0.0.7.dist-info/METADATA
junto_utils-0.0.7.dist-info/RECORD
junto_utils-0.0.7.dist-info/WHEEL
junto_utils-0.0.7.dist-info/metadata.json
junto_utils-0.0.7.dist-info/top_level.txt
