Metadata-Version: 2.0
Name: junto-utils
Version: 0.0.7
Summary: Utils for Junto projects
Home-page: https://github.com/junto-team/JuntoUtils
Author: Timofey Katalnikov
Author-email: kattimofey@gmail.com
License: UNKNOWN
Platform: UNKNOWN
Classifier: Programming Language :: Python :: 3
Classifier: License :: OSI Approved :: MIT License
Classifier: Operating System :: OS Independent
Requires-Dist: Django (>=2.1)
Requires-Dist: Pillow (>=5.4)
Requires-Dist: djangorestframework (>=3.9)
